easycm/__init__.py
easycm/utils.py
easycm-0.0.5.dist-info/LICENSE
easycm-0.0.5.dist-info/METADATA
easycm-0.0.5.dist-info/WHEEL
easycm-0.0.5.dist-info/top_level.txt
easycm-0.0.5.dist-info/RECORD
