Metadata-Version: 2.1
Name: easycm
Version: 0.0.5
Summary: A simple python package to plot confusion matrices
Home-page: https://github.com/vhrique/easycm
Author: Victor Henrique Alves Ribeiro
License: BSD-3
Project-URL: Source, https://github.com/vhrique/easycm
Project-URL: Tracker, https://github.com/vhrique/easycm/issues
Platform: UNKNOWN
License-File: LICENSE
